obj2bin/__init__.py
obj2bin/__version__.py
obj2bin/obj2bin.py
obj2bin-0.0.3.dist-info/LICENSE
obj2bin-0.0.3.dist-info/METADATA
obj2bin-0.0.3.dist-info/WHEEL
obj2bin-0.0.3.dist-info/top_level.txt
obj2bin-0.0.3.dist-info/RECORD
