Metadata-Version: 2.1
Name: obj2bin
Version: 0.0.3
Summary: A simple object serialization library
Author: hexdhog
License: MIT
Classifier: Programming Language :: Python :: 3
Classifier: License :: OSI Approved :: MIT License
Requires-Python: >=3.7
License-File: LICENSE
Provides-Extra: linting
Requires-Dist: mypy ; extra == 'linting'
Requires-Dist: ruff ; extra == 'linting'
